{"web":{"client_id":"362835825237-bbb7o6tj0lkgnu0l383bld5tab5v17qt.apps.googleusercontent.com","project_id":"evident-healer-302510","auth_uri":"https://accounts.google.com/o/oauth2/auth","token_uri":"https://oauth2.googleapis.com/token","auth_provider_x509_cert_url":"https://www.googleapis.com/oauth2/v1/certs","client_secret":"Wpw6NZw7SyeeQTJekei4ntx5","redirect_uris":["http://ec2-3-17-147-125.us-east-2.compute.amazonaws.com:8081/callBack"],"javascript_origins":["http://ec2-3-17-147-125.us-east-2.compute.amazonaws.com:8080"]}}